logging_slacker/__init__.py
logging_slacker/colors.py
logging_slacker/formatters.py
logging_slacker-0.1.0.dist-info/LICENSE
logging_slacker-0.1.0.dist-info/METADATA
logging_slacker-0.1.0.dist-info/WHEEL
logging_slacker-0.1.0.dist-info/top_level.txt
logging_slacker-0.1.0.dist-info/RECORD
