Metadata-Version: 2.1
Name: logging-slacker
Version: 0.1.0
Summary: Posts log events to Slack via API
Home-page: https://github.com/s3m3dov/logging_slacker
Download-URL: https://github.com/s3m3dov/logging_slacker/archive/0.1.0.tar.gz
Author: Hikmat Samadov
Author-email: hikmat@cublya.com
Keywords: slack,logging
Classifier: Development Status :: 5 - Production/Stable
Classifier: Environment :: Web Environment
Classifier: Framework :: Django
Classifier: Intended Audience :: Developers
Classifier: Intended Audience :: System Administrators
Classifier: License :: OSI Approved :: Apache Software License
Classifier: Natural Language :: English
Classifier: Operating System :: OS Independent
Classifier: Programming Language :: Python
Classifier: Programming Language :: Python :: 2
Classifier: Programming Language :: Python :: 3
Classifier: Topic :: Communications :: Chat
Classifier: Topic :: Office/Business :: Groupware
License-File: LICENSE
Requires-Dist: slack-sdk >=3.17.2
Requires-Dist: six >=1.11.0
